networkparse/__init__.py
networkparse/core.py
networkparse/parse.py
networkparse-1.9.0.dist-info/LICENSE
networkparse-1.9.0.dist-info/WHEEL
networkparse-1.9.0.dist-info/METADATA
networkparse-1.9.0.dist-info/RECORD
